MANIFEST.in
README.md
setup.py
django_auth_pubtkt/__init__.py
django_auth_pubtkt/auth_pubtkt.py
django_auth_pubtkt/middleware.py
django_auth_pubtkt/urls.py
django_auth_pubtkt/views.py
django_auth_pubtkt.egg-info/PKG-INFO
django_auth_pubtkt.egg-info/SOURCES.txt
django_auth_pubtkt.egg-info/dependency_links.txt
django_auth_pubtkt.egg-info/requires.txt
django_auth_pubtkt.egg-info/top_level.txt
tests/__init__.py
tests/models.py
tests/test_settings.py
tests/tests.py
tests/urls.py
tests/views.py