Metadata-Version: 1.1
Name: django-auth-pubtkt
Version: 2.0.1
Summary: Implementation of mod_auth_pubtkt as Django middleware
Home-page: https://github.com/Baguage/django-auth-pubtkt
Author: Alexander Vyushkov
Author-email: alex.vyushkov@gmail.com
License: BSD
Keywords: django auth mod_auth_pubtkt
Platform: UNKNOWN
Classifier: Development Status :: 5 - Production/Stable
Classifier: Environment :: Web Environment
Classifier: Programming Language :: Python
Classifier: Framework :: Django
Classifier: Topic :: Internet :: WWW/HTTP :: WSGI :: Middleware
Classifier: Topic :: Software Development :: Libraries :: Python Modules
Classifier: License :: OSI Approved :: Apache Software License
